mlip_arena/__init__.py
mlip_arena/data/__init__.py
mlip_arena/data/collate.py
mlip_arena/data/local.py
mlip_arena/flows/__init__.py
mlip_arena/flows/diatomics.py
mlip_arena/jobs/__init__.py
mlip_arena/jobs/run.py
mlip_arena/models/README.md
mlip_arena/models/__init__.py
mlip_arena/models/mace.py
mlip_arena/models/registry.yaml
mlip_arena/models/utils.py
mlip_arena/models/classicals/__init__.py
mlip_arena/models/classicals/zbl.py
mlip_arena/models/externals/__init__.py
mlip_arena/models/externals/alignn.py
mlip_arena/models/externals/ani.py
mlip_arena/models/externals/chgnet.py
mlip_arena/models/externals/deepmd.py
mlip_arena/models/externals/equiformer.py
mlip_arena/models/externals/escn.py
mlip_arena/models/externals/fairchem.py
mlip_arena/models/externals/mace-mp.py
mlip_arena/models/externals/mace-off.py
mlip_arena/models/externals/matgl.py
mlip_arena/models/externals/mattersim.py
mlip_arena/models/externals/orb.py
mlip_arena/models/externals/sevennet.py
mlip_arena/tasks/README.md
mlip_arena/tasks/__init__.py
mlip_arena/tasks/elasticity.py
mlip_arena/tasks/eos.py
mlip_arena/tasks/md.py
mlip_arena/tasks/neb.py
mlip_arena/tasks/optimize.py
mlip_arena/tasks/phonon.py
mlip_arena/tasks/registry.yaml
mlip_arena/tasks/utils.py
mlip_arena/tasks/combustion/H256O128.extxyz
mlip_arena/tasks/combustion/__init__.py
mlip_arena/tasks/combustion/flow.py
mlip_arena/tasks/combustion/water.ipynb
mlip_arena/tasks/diatomics/__init__.py
mlip_arena/tasks/diatomics/analysis.py
mlip_arena/tasks/diatomics/flow.py
mlip_arena/tasks/diatomics/homonuclear-diatomics.tex
mlip_arena/tasks/diatomics/run.ipynb
mlip_arena/tasks/diatomics/alignn/homonuclear-diatomics.json
mlip_arena/tasks/diatomics/ani/homonuclear-diatomics.json
mlip_arena/tasks/diatomics/chgnet/homonuclear-diatomics.json
mlip_arena/tasks/diatomics/equiformer/homonuclear-diatomics.json
mlip_arena/tasks/diatomics/escn/homonuclear-diatomics.json
mlip_arena/tasks/diatomics/fairchem/homonuclear-diatomics.json
mlip_arena-0.1.3.dist-info/licenses/LICENSE
mlip_arena-0.1.3.dist-info/WHEEL
mlip_arena-0.1.3.dist-info/METADATA
mlip_arena-0.1.3.dist-info/RECORD
