Metadata-Version: 2.4
Name: mlip-arena
Version: 0.1.3
Summary: Fair and transparent benchmark of machine learning interatomic potentials (MLIPs), beyond error-based regression metrics
Keywords: pytorch,machine-learning-interatomic-potentials,huggingface,deep-learning,graph-neural-networks
Author-email: Yuan Chiang <cyrusyc@lbl.gov>
Requires-Python: >=3.9
Classifier: Development Status :: 1 - Planning
Classifier: Programming Language :: Python
Classifier: Programming Language :: Python :: 3.10
Classifier: Programming Language :: Python :: 3.11
Classifier: Programming Language :: Python :: 3.12
Classifier: Programming Language :: Python :: 3 :: Only
License-File: LICENSE
Requires-Dist: loguru
Requires-Dist: ase>=3.26.0
Requires-Dist: pymatgen
Requires-Dist: torch
Requires-Dist: huggingface_hub
Requires-Dist: datasets
Requires-Dist: safetensors
Requires-Dist: prefect[dask]
Requires-Dist: dask
Requires-Dist: dask_jobqueue
Requires-Dist: tables
Requires-Dist: MDAnalysis
Requires-Dist: streamlit==1.43.2 ; extra == "app"
Requires-Dist: plotly ; extra == "app"
Requires-Dist: torch==2.2.0 ; extra == "deepmd"
Requires-Dist: deepmd-kit ; extra == "deepmd"
Requires-Dist: hydra-core ; extra == "fairchem"
Requires-Dist: fairchem-core==1.10.0 ; extra == "fairchem"
Requires-Dist: mace-torch==0.3.12 ; extra == "mace"
Requires-Dist: matgl==1.2.6 ; extra == "matgl"
Requires-Dist: orb-models==0.4.0 ; extra == "orb"
Requires-Dist: pynanoflann ; extra == "orb"
Requires-Dist: torch==2.4.0 ; extra == "test"
Requires-Dist: torch_dftd==0.4.0 ; extra == "test"
Requires-Dist: e3nn==0.5.0 ; extra == "test"
Requires-Dist: dgl ; extra == "test"
Requires-Dist: chgnet==0.3.8 ; extra == "test"
Requires-Dist: sevenn==0.9.3.post1 ; extra == "test"
Requires-Dist: alignn==2024.5.27 ; extra == "test"
Requires-Dist: mattersim==1.1.2 ; extra == "test"
Requires-Dist: torchani==2.2.4 ; extra == "test"
Requires-Dist: pytest ; extra == "test"
Requires-Dist: pytest-xdist ; extra == "test"
Requires-Dist: prefect==3.2.13 ; extra == "test"
Requires-Dist: pymatgen>=2025.1.9 ; extra == "test"
Requires-Dist: MDAnalysis ; extra == "test"
Requires-Dist: streamlit==1.43.2 ; extra == "test"
Project-URL: Homepage, https://github.com/atomind-ai/mlip-arena
Project-URL: Issues, https://github.com/atomind-ai/mlip-arena/issues
Provides-Extra: app
Provides-Extra: deepmd
Provides-Extra: fairchem
Provides-Extra: mace
Provides-Extra: matgl
Provides-Extra: orb
Provides-Extra: test
